design_insight_builder/__init__.py
design_insight_builder/main.py
design_insight_builder/prompts.py
design_insight_builder-2025.12.21114125.dist-info/METADATA
design_insight_builder-2025.12.21114125.dist-info/WHEEL
design_insight_builder-2025.12.21114125.dist-info/top_level.txt
design_insight_builder-2025.12.21114125.dist-info/RECORD
