Metadata-Version: 2.4
Name: design-insight-builder
Version: 2025.12.21114125
Summary: A new package that helps users extract and organize practical design tips from text inputs. Users can input text containing design advice, and the package will use llmatch-messages to process the info
Author-email: design-insight-builder <hi@eugene.plus>
License: MIT
Project-URL: Homepage, https://github.com/chigwell/design-insight-builder
Requires-Python: >=3.9
Requires-Dist: langchain-llm7>=0.0.0
Requires-Dist: llmatch-messages>=0.0.0
Requires-Dist: langchain-core>=0.3.0
